{
    "SN2009bx": {
        "name": "SN2009bx",
        "aliases": [
            "SN2009bx",
            "CSS090216:100910+075434"
        ],
        "sources": [
            {
                "name": "Asiago Supernova Catalogue",
                "url": "http://graspa.oapd.inaf.it/cgi-bin/sncat.php",
                "alias": "1",
                "secondary": true
            },
            {
                "name": "CBET 1744",
                "url": "http://www.cbat.eps.harvard.edu/iau/cbet/001700/CBET001744.txt",
                "alias": "2"
            },
            {
                "name": "Latest Supernovae",
                "url": "http://www.rochesterastronomy.org/snimages/snredshiftall.html",
                "alias": "3",
                "secondary": true
            },
            {
                "name": "2012A&A...538A.120L",
                "url": "http://adsabs.harvard.edu/abs/2012A&A...538A.120L",
                "bibcode": "2012A&A...538A.120L",
                "alias": "4"
            }
        ],
        "claimedtype": [
            {
                "value": "Ia",
                "source": "1"
            }
        ],
        "discoverday": "15",
        "discoverer": "CRTS",
        "discovermonth": "2",
        "discoveryear": "2009",
        "galdec": "+075434",
        "galra": "100910",
        "host": [
            {
                "value": "A100910+0754",
                "source": "1"
            },
            {
                "value": "(SDSSJ100910.19+75433.9)",
                "source": "4"
            }
        ],
        "hvel": [
            {
                "value": "21000",
                "source": "1"
            }
        ],
        "lumdist": "300",
        "maxabsmag": "-20",
        "maxappmag": "18.7",
        "maxday": "15",
        "maxmonth": "2",
        "maxyear": "2009",
        "redshift": [
            {
                "value": "0.07",
                "source": "2,3,4"
            }
        ],
        "sndec": "+07:54:34.4",
        "snra": "10:09:10.10",
        "photometry": [
            {
                "timeunit": "MJD",
                "time": "54877.5",
                "band": "",
                "abmag": "18.7",
                "source": "2,3"
            }
        ]
    }
}