{
    "SN2006kv": {
        "name": "SN2006kv",
        "aliases": [
            "SN2006kv"
        ],
        "sources": [
            {
                "name": "Asiago Supernova Catalogue",
                "url": "http://graspa.oapd.inaf.it/cgi-bin/sncat.php",
                "alias": "1",
                "secondary": true
            },
            {
                "name": "<a href='http://www.cbat.eps.harvard.edu/iau/cbet/000600/CBET000688.txt'>CBET 688</a>",
                "alias": "2"
            },
            {
                "name": "Latest Supernovae",
                "url": "http://www.rochesterastronomy.org/snimages/snredshiftall.html",
                "alias": "3",
                "secondary": true
            },
            {
                "name": "2012A&A...538A.120L",
                "url": "http://adsabs.harvard.edu/abs/2012A&A...538A.120L",
                "bibcode": "2012A&A...538A.120L",
                "alias": "4"
            }
        ],
        "claimedtype": [
            {
                "value": "II",
                "source": "1,2,3"
            }
        ],
        "discoverday": "15",
        "discoverer": "SDSS Collaboration",
        "discovermonth": "10",
        "discoveryear": "2006",
        "galdec": "+005449",
        "galra": "000306",
        "host": [
            {
                "value": "A000306+0054",
                "source": "1"
            }
        ],
        "maxappmag": "19.5",
        "maxday": "15",
        "maxmonth": "10",
        "maxyear": "2006",
        "sndec": "+00:54:49.6",
        "snra": "00:03:06.66",
        "photometry": [
            {
                "timeunit": "MJD",
                "time": "54023.5",
                "band": "",
                "abmag": "19.5",
                "source": "2,3"
            }
        ]
    }
}