{
    "SN2009lj": {
        "name": "SN2009lj",
        "aliases": [
            "SN2009lj"
        ],
        "sources": [
            {
                "name": "Asiago Supernova Catalogue",
                "url": "http://graspa.oapd.inaf.it/cgi-bin/sncat.php",
                "alias": "1",
                "secondary": true
            },
            {
                "name": "<a href='http://www.cbat.eps.harvard.edu/cbet/002000/CBET002027.txt'>CBET 2027</a>",
                "alias": "2"
            },
            {
                "name": "Latest Supernovae",
                "url": "http://www.rochesterastronomy.org/snimages/snredshiftall.html",
                "alias": "3",
                "secondary": true
            },
            {
                "name": "2012A&A...538A.120L",
                "url": "http://adsabs.harvard.edu/abs/2012A&A...538A.120L",
                "bibcode": "2012A&A...538A.120L",
                "alias": "4"
            }
        ],
        "claimedtype": [
            {
                "value": "Ic",
                "source": "1,2,3"
            }
        ],
        "discoverday": "12",
        "discoverer": "LOSS",
        "discovermonth": "11",
        "discoveryear": "2009",
        "galdec": "+391908",
        "galra": "031233",
        "host": [
            {
                "value": "NGC 1233",
                "source": "1,2,3"
            }
        ],
        "hvel": [
            {
                "value": "4465",
                "source": "1"
            }
        ],
        "lumdist": "65.3",
        "maxabsmag": "-15.3",
        "maxappmag": "18.8",
        "maxday": "12",
        "maxmonth": "11",
        "maxyear": "2009",
        "redshift": [
            {
                "value": "0.0146",
                "source": "2,3"
            }
        ],
        "sndec": "+39:18:42.0",
        "snra": "03:12:32.49",
        "photometry": [
            {
                "timeunit": "MJD",
                "time": "55147.5",
                "band": "",
                "abmag": "18.8",
                "source": "2,3"
            }
        ]
    }
}