{
    "SN2007us": {
        "name": "SN2007us",
        "aliases": [
            "SN2007us"
        ],
        "sources": [
            {
                "name": "Asiago Supernova Catalogue",
                "url": "http://graspa.oapd.inaf.it/cgi-bin/sncat.php",
                "alias": "1",
                "secondary": true
            },
            {
                "name": "CBET 1186",
                "url": "http://www.cbat.eps.harvard.edu/iau/cbet/001100/CBET001186.txt",
                "alias": "2"
            },
            {
                "name": "Latest Supernovae",
                "url": "http://www.rochesterastronomy.org/snimages/snredshiftall.html",
                "alias": "3",
                "secondary": true
            },
            {
                "name": "2012A&A...538A.120L",
                "url": "http://adsabs.harvard.edu/abs/2012A&A...538A.120L",
                "bibcode": "2012A&A...538A.120L",
                "alias": "4"
            }
        ],
        "claimedtype": [
            {
                "value": "Ia",
                "source": "1,2,3"
            }
        ],
        "discoverday": "6",
        "discoverer": "ESSENCE project",
        "discovermonth": "12",
        "discoveryear": "2007",
        "galdec": "-080055",
        "galra": "022754",
        "host": [
            {
                "value": "A022754-0800",
                "source": "1"
            },
            {
                "value": "(SDSSJ022754.86-80055.6)",
                "source": "4"
            }
        ],
        "hvel": [
            {
                "value": "100000",
                "source": "D"
            }
        ],
        "lumdist": [
            {
                "value": "4000",
                "source": "D"
            }
        ],
        "maxabsmag": "-20",
        "maxappmag": "22.5",
        "maxday": "6",
        "maxmonth": "12",
        "maxyear": "2007",
        "redshift": [
            {
                "value": "0.6",
                "source": "1,2,3,4"
            }
        ],
        "sndec": "-08:00:55.24",
        "snra": "02:27:54.866",
        "photometry": [
            {
                "timeunit": "MJD",
                "time": "54440.5",
                "band": "",
                "abmag": "22.5",
                "source": "2,3"
            }
        ]
    }
}