{
    "SN2007gh": {
        "name": "SN2007gh",
        "aliases": [
            "SN2007gh"
        ],
        "sources": [
            {
                "name": "Asiago Supernova Catalogue",
                "url": "http://graspa.oapd.inaf.it/cgi-bin/sncat.php",
                "alias": "1",
                "secondary": true
            },
            {
                "name": "CBET 1014",
                "url": "http://www.cbat.eps.harvard.edu/cbet/001000/CBET001014.txt",
                "alias": "2"
            },
            {
                "name": "Latest Supernovae",
                "url": "http://www.rochesterastronomy.org/snimages/snredshiftall.html",
                "alias": "3",
                "secondary": true
            },
            {
                "name": "2012A&A...538A.120L",
                "url": "http://adsabs.harvard.edu/abs/2012A&A...538A.120L",
                "bibcode": "2012A&A...538A.120L",
                "alias": "4"
            }
        ],
        "claimedtype": [
            {
                "value": "II",
                "source": "1,2,3"
            }
        ],
        "discoverday": "27",
        "discoverer": "Nearby Supernova Factory",
        "discovermonth": "7",
        "discoveryear": "2007",
        "galdec": "+021959",
        "galra": "021031",
        "host": [
            {
                "value": "A021031+0219",
                "source": "1"
            },
            {
                "value": "(PGC1223593)",
                "source": "4"
            }
        ],
        "hvel": [
            {
                "value": "6000",
                "source": "1"
            }
        ],
        "lumdist": "90",
        "maxabsmag": "-20",
        "maxappmag": "19.1",
        "maxday": "27",
        "maxmonth": "7",
        "maxyear": "2007",
        "redshift": [
            {
                "value": "0.02",
                "source": "2,3,4"
            }
        ],
        "sndec": "+02:19:59.3",
        "snra": "02:10:31.08",
        "photometry": [
            {
                "timeunit": "MJD",
                "time": "54308.5",
                "band": "",
                "abmag": "19.1",
                "source": "2,3"
            }
        ]
    }
}