{
    "SN2006ty": {
        "name": "SN2006ty",
        "aliases": [
            "SN2006ty"
        ],
        "sources": [
            {
                "name": "Asiago Supernova Catalogue",
                "url": "http://graspa.oapd.inaf.it/cgi-bin/sncat.php",
                "alias": "1",
                "secondary": true
            },
            {
                "name": "CBET 830",
                "url": "http://www.cbat.eps.harvard.edu/iau/cbet/000800/CBET000830.txt",
                "alias": "2"
            },
            {
                "name": "Latest Supernovae",
                "url": "http://www.rochesterastronomy.org/snimages/snredshiftall.html",
                "alias": "3",
                "secondary": true
            },
            {
                "name": "2012A&A...538A.120L",
                "url": "http://adsabs.harvard.edu/abs/2012A&A...538A.120L",
                "bibcode": "2012A&A...538A.120L",
                "alias": "4"
            }
        ],
        "claimedtype": [
            {
                "value": "Ia",
                "source": "1,2,3"
            }
        ],
        "discoverday": "20",
        "discoverer": "ESSENCE project",
        "discovermonth": "12",
        "discoveryear": "2006",
        "galdec": "+003404",
        "galra": "011045",
        "host": [
            {
                "value": "A011045+0034",
                "source": "1"
            }
        ],
        "hvel": [
            {
                "value": "52000",
                "source": "D"
            }
        ],
        "lumdist": [
            {
                "value": "960",
                "source": "D"
            }
        ],
        "maxabsmag": "-19",
        "maxappmag": "20.5",
        "maxday": "20",
        "maxmonth": "12",
        "maxyear": "2006",
        "redshift": [
            {
                "value": "0.19",
                "source": "1,2,3,4"
            }
        ],
        "sndec": "+00:34:04.46",
        "snra": "01:10:45.362",
        "photometry": [
            {
                "timeunit": "MJD",
                "time": "54089.5",
                "band": "",
                "abmag": "20.5",
                "source": "2,3"
            }
        ]
    }
}