{
    "SN2006qg": {
        "name": "SN2006qg",
        "aliases": [
            "SN2006qg"
        ],
        "sources": [
            {
                "name": "Asiago Supernova Catalogue",
                "url": "http://graspa.oapd.inaf.it/cgi-bin/sncat.php",
                "alias": "1",
                "secondary": true
            },
            {
                "name": "CBET 762",
                "url": "http://www.cbat.eps.harvard.edu/iau/cbet/000700/CBET000762.txt",
                "alias": "2"
            },
            {
                "name": "Latest Supernovae",
                "url": "http://www.rochesterastronomy.org/snimages/snredshiftall.html",
                "alias": "3",
                "secondary": true
            },
            {
                "name": "2012A&A...538A.120L",
                "url": "http://adsabs.harvard.edu/abs/2012A&A...538A.120L",
                "bibcode": "2012A&A...538A.120L",
                "alias": "4"
            }
        ],
        "claimedtype": [
            {
                "value": "Ia",
                "source": "1,2,3"
            }
        ],
        "discoverday": "17",
        "discoverer": "SDSS Collaboration",
        "discovermonth": "11",
        "discoveryear": "2006",
        "galdec": "+002649",
        "galra": "215418",
        "host": [
            {
                "value": "A215418+0026",
                "source": "1"
            }
        ],
        "hvel": [
            {
                "value": "61000",
                "source": "D"
            }
        ],
        "lumdist": [
            {
                "value": "1200",
                "source": "D"
            }
        ],
        "maxabsmag": "-18",
        "maxappmag": "22",
        "maxday": "17",
        "maxmonth": "11",
        "maxyear": "2006",
        "redshift": [
            {
                "value": "0.23",
                "source": "1,2,3,4"
            }
        ],
        "sndec": "+00:26:49.2",
        "snra": "21:54:18.09",
        "photometry": [
            {
                "timeunit": "MJD",
                "time": "54056.5",
                "band": "",
                "abmag": "22.0",
                "source": "2,3"
            }
        ]
    }
}