{
    "SN2007dz": {
        "name": "SN2007dz",
        "aliases": [
            "SN2007dz"
        ],
        "sources": [
            {
                "name": "http://graspa.oapd.inaf.it/cgi-bin/sncat.php",
                "alias": "1",
                "secondary": true
            },
            {
                "name": "<a href='http://www.rochesterastronomy.org/snimages/snredshiftall.html'>Latest Supernovae</a>",
                "alias": "2",
                "secondary": true
            },
            {
                "name": "<a href='http://www.cbat.eps.harvard.edu/iau/cbet/000900/CBET000990.txt'>CBET 990</a>",
                "alias": "3"
            },
            {
                "name": "Pro",
                "alias": "4"
            },
            {
                "name": "<a href='http://adsabs.harvard.edu/abs/2012A%26A...538A.120L'>2012A&A...538A.120L</a>",
                "alias": "5"
            }
        ],
        "claimedtype": [
            {
                "type": "Ia",
                "source": "1,2"
            }
        ],
        "discoverday": "12",
        "discoverer": "Nearby Supernova Factory",
        "discovermonth": "5",
        "discoveryear": "2007",
        "galdec": "+110248",
        "galra": "214516",
        "host": "A214516+1102",
        "hvel": "9000",
        "lumdist": "140",
        "maxabsmag": "-18",
        "maxappmag": "17.9",
        "maxday": "12",
        "maxmonth": "5",
        "maxyear": "2007",
        "redshift": "0.03",
        "sndec": "+11:02:48.6",
        "snra": "21:45:16.26",
        "photometry": [
            {
                "timeunit": "MJD",
                "time": "54232.5",
                "band": "",
                "abmag": "17.9",
                "source": "3,2"
            },
            {
                "timeunit": "MJD",
                "time": "54289.991",
                "band": "CR",
                "abmag": "17.9",
                "source": "4,2"
            }
        ]
    }
}