{
    "SN2006ro": {
        "name": "SN2006ro",
        "aliases": [
            "SN2006ro"
        ],
        "sources": [
            {
                "name": "Asiago Supernova Catalogue",
                "url": "http://graspa.oapd.inaf.it/cgi-bin/sncat.php",
                "alias": "1",
                "secondary": true
            },
            {
                "name": "CBET 768",
                "url": "http://www.cbat.eps.harvard.edu/iau/cbet/000700/CBET000768.txt",
                "alias": "2"
            },
            {
                "name": "Latest Supernovae",
                "url": "http://www.rochesterastronomy.org/snimages/snredshiftall.html",
                "alias": "3",
                "secondary": true
            },
            {
                "name": "2012A&A...538A.120L",
                "url": "http://adsabs.harvard.edu/abs/2012A&A...538A.120L",
                "bibcode": "2012A&A...538A.120L",
                "alias": "4"
            }
        ],
        "claimedtype": [
            {
                "value": "Ia",
                "source": "1,2,3"
            }
        ],
        "discoverday": "8",
        "discoverer": "Nearby Supernova Factory",
        "discovermonth": "11",
        "discoveryear": "2006",
        "galdec": "+265005",
        "galra": "035116",
        "host": [
            {
                "value": "A035116+2650",
                "source": "1"
            }
        ],
        "hvel": [
            {
                "value": "31000",
                "source": "D"
            }
        ],
        "lumdist": "530",
        "maxabsmag": "-19",
        "maxappmag": "19.8",
        "maxday": "8",
        "maxmonth": "11",
        "maxyear": "2006",
        "redshift": [
            {
                "value": "0.11",
                "source": "1,2,3,4"
            }
        ],
        "sndec": "+26:50:05.4",
        "snra": "03:51:16.85",
        "photometry": [
            {
                "timeunit": "MJD",
                "time": "54047.5",
                "band": "",
                "abmag": "19.8",
                "source": "2,3"
            }
        ]
    }
}