{
    "SN2006ss": {
        "name": "SN2006ss",
        "aliases": [
            "SN2006ss"
        ],
        "sources": [
            {
                "name": "http://graspa.oapd.inaf.it/cgi-bin/sncat.php",
                "alias": "1",
                "secondary": true
            },
            {
                "name": "<a href='http://www.rochesterastronomy.org/snimages/snredshiftall.html'>Latest Supernovae</a>",
                "alias": "2",
                "secondary": true
            },
            {
                "name": "<a href='http://www.cbat.eps.harvard.edu/iauc/08700/08789.html#Item1'>IAUC 8789</a>",
                "alias": "3"
            },
            {
                "name": "TON",
                "alias": "4"
            },
            {
                "name": "<a href='http://adsabs.harvard.edu/abs/2012A%26A...538A.120L'>2012A&A...538A.120L</a>",
                "alias": "5"
            }
        ],
        "claimedtype": [
            {
                "type": "IIb",
                "source": "1,2"
            }
        ],
        "discoverday": "16",
        "discoverer": "Tom Boles",
        "discovermonth": "12",
        "discoveryear": "2006",
        "galdec": "+351120",
        "galra": "142026",
        "host": "NGC 5579",
        "hvel": "3591",
        "lumdist": "53.82",
        "maxabsmag": "-17.155",
        "maxappmag": "16.5",
        "maxday": "21",
        "maxmonth": "12",
        "maxyear": "2006",
        "redshift": "0.01205",
        "sndec": "+35:11:42.7",
        "snra": "14:20:27.46",
        "photometry": [
            {
                "timeunit": "MJD",
                "time": "54085.5",
                "band": "",
                "abmag": "17.6",
                "source": "3,2"
            },
            {
                "timeunit": "MJD",
                "time": "54090.198",
                "band": "CR",
                "abmag": "16.5",
                "source": "4,2"
            }
        ]
    }
}